carb_builder/__init__.py
carb_builder/builder.py
carb_builder/example.py
carb_builder/geometry.py
carb_builder/residue.py
carb_builder/simulation.py
carb_builder/utils.py
carb_builder-0.1.2.dist-info/METADATA
carb_builder-0.1.2.dist-info/WHEEL
carb_builder-0.1.2.dist-info/top_level.txt
carb_builder-0.1.2.dist-info/RECORD
