Metadata-Version: 2.1
Name: carb_builder
Version: 0.1.2
Summary: A Python package for building and simulating carbohydrate structures.
Author: Ayodele Faleti
Author-email: ayodele.ayodele@gmail.com
Classifier: Development Status :: 3 - Alpha
Classifier: Intended Audience :: Science/Research
Classifier: License :: OSI Approved :: MIT License
Classifier: Programming Language :: Python :: 3
Classifier: Programming Language :: Python :: 3.6
Classifier: Programming Language :: Python :: 3.7
Classifier: Programming Language :: Python :: 3.8
Classifier: Programming Language :: Python :: 3.9
Requires-Python: >=3.6
Requires-Dist: openmm
Requires-Dist: numpy
